memoize_compat/__init__.py
django_memoize_compat-3.0.1.dist-info/LICENSE
django_memoize_compat-3.0.1.dist-info/METADATA
django_memoize_compat-3.0.1.dist-info/WHEEL
django_memoize_compat-3.0.1.dist-info/RECORD
