Metadata-Version: 2.1
Name: django-memoize-compat
Version: 3.0.1
Summary: a modern, maintained drop-in replacement for the abandoned django-memoize package.
Home-page: https://github.com/rdnve/django-memoize-compat
License: BSD-3-Clause
Keywords: django,cache,memoize,redis,performance
Author: serje u
Author-email: pleaseanswermeserjeu@icloud.com
Requires-Python: >=3.12,<3.14
Classifier: Development Status :: 4 - Beta
Classifier: Environment :: Web Environment
Classifier: Framework :: Django
Classifier: Framework :: Django :: 5.0
Classifier: Intended Audience :: Developers
Classifier: License :: OSI Approved :: BSD License
Classifier: Natural Language :: English
Classifier: Operating System :: OS Independent
Classifier: Programming Language :: Python :: 3
Classifier: Programming Language :: Python :: 3.12
Classifier: Programming Language :: Python :: 3.13
Classifier: Topic :: Internet :: WWW/HTTP
Classifier: Topic :: Software Development :: Libraries
Requires-Dist: django (>=4.2)
Project-URL: Repository, https://github.com/rdnve/django-memoize-compat
